aiogrpc/__init__.py
aiogrpc/channel.py
aiogrpc/utils.py
aiogrpc-1.7.dist-info/LICENSE
aiogrpc-1.7.dist-info/METADATA
aiogrpc-1.7.dist-info/WHEEL
aiogrpc-1.7.dist-info/top_level.txt
aiogrpc-1.7.dist-info/RECORD
