Metadata-Version: 1.2
Name: aiogrpc
Version: 1.7
Summary: asyncio wrapper for grpc.io
Home-page: https://github.com/hubo1016/aiogrpc
Author: Hu Bo
Author-email: hubo1016@126.com
License: Apache
Platform: any
Classifier: License :: OSI Approved :: MIT License
Classifier: Intended Audience :: Developers
Classifier: Framework :: AsyncIO
Classifier: Programming Language :: Python
Classifier: Programming Language :: Python :: 3
Classifier: Programming Language :: Python :: 3.6
Classifier: Topic :: Software Development
Classifier: Framework :: AsyncIO
Requires-Python: >=3.6
